setup.py
buffer/__init__.py
buffer/client.py
buffer_alpaca.egg-info/PKG-INFO
buffer_alpaca.egg-info/SOURCES.txt
buffer_alpaca.egg-info/dependency_links.txt
buffer_alpaca.egg-info/requires.txt
buffer_alpaca.egg-info/top_level.txt