Metadata-Version: 1.1
Name: buffer-alpaca
Version: 0.1.0
Summary: Buffer API library client for python
Home-page: https://bufferapp.com
Author: Pavan Kumar Sunkara
Author-email: pavan.sss1991@gmail.com
License: MIT
Platform: UNKNOWN
Classifier: Development Status :: 5 - Production/Stable
Classifier: Intended Audience :: Developers
Classifier: License :: OSI Approved :: MIT License
Classifier: Operating System :: OS Independent
Classifier: Programming Language :: Python :: 2.6
Classifier: Programming Language :: Python :: 2.7
Classifier: Programming Language :: Python :: 3.2
Classifier: Programming Language :: Python :: 3.3
Classifier: Topic :: Software Development :: Libraries :: Python Modules
